kwargparse.py
kwargparse-1.0.0.dist-info/LICENSE
kwargparse-1.0.0.dist-info/METADATA
kwargparse-1.0.0.dist-info/WHEEL
kwargparse-1.0.0.dist-info/top_level.txt
kwargparse-1.0.0.dist-info/RECORD
