Metadata-Version: 2.1
Name: kwargparse
Version: 1.0.0
Summary: Parser that parses Python's kwargs similar to the way done by setuptools, while exporting an interface like argparse
Home-page: UNKNOWN
Author: Gaming32
Author-email: gaming32i64@gmail.com
License: License :: OSI Approved :: MIT License
Platform: UNKNOWN
